LICENSE
README.md
pyproject.toml
src/hyperion_node/__init__.py
src/hyperion_node/main.py
src/hyperion_node.egg-info/PKG-INFO
src/hyperion_node.egg-info/SOURCES.txt
src/hyperion_node.egg-info/dependency_links.txt
src/hyperion_node.egg-info/entry_points.txt
src/hyperion_node.egg-info/requires.txt
src/hyperion_node.egg-info/top_level.txt