Metadata-Version: 2.4
Name: hyperion-node
Version: 0.1.0
Summary: Add your description here
Author-email: Arian-Ott <arian.ott@ieee.org>
Requires-Python: >=3.14
License-File: LICENSE
Requires-Dist: click>=8.3.1
Requires-Dist: pyartnet>=2.0
Requires-Dist: requests>=2.32.5
Requires-Dist: websockets>=16.0
Dynamic: license-file
